README.md
setup.py
aiorazemax/__init__.py
aiorazemax/__version__.py
aiorazemax/consumers.py
aiorazemax/drivers.py
aiorazemax/event_manager.py
aiorazemax/exceptions.py
aiorazemax/publisher.py
aiorazemax.egg-info/PKG-INFO
aiorazemax.egg-info/SOURCES.txt
aiorazemax.egg-info/dependency_links.txt
aiorazemax.egg-info/requires.txt
aiorazemax.egg-info/top_level.txt